nbadge/__init__.py
nbadge/cli.py
nbadge/constants.py
nbadge-0.1.3.dist-info/entry_points.txt
nbadge-0.1.3.dist-info/WHEEL
nbadge-0.1.3.dist-info/METADATA
nbadge-0.1.3.dist-info/license_files/LICENSE
nbadge-0.1.3.dist-info/RECORD
