Metadata-Version: 2.1
Name: nbadge
Version: 0.1.3
Summary: A Python CLI to generate Jupyter notebook badges for different services.
License: MIT
Author-email: João Palmeiro <joaopalmeiro@proton.me>
Requires-Python: >=3.7
Requires-Dist: click>=8.1.3
Requires-Dist: giturlparse>=0.10.0
Requires-Dist: pyperclip>=1.8.2
Project-URL: Homepage, https://github.com/joaopalmeiro/nbadge
Project-URL: Repository, https://github.com/joaopalmeiro/nbadge
